aviary/__init__.py
aviary/api.py
aviary/constants.py
aviary/run_all_benchmarks.py
aviary/core/AviaryGroup.py
aviary/core/PostMissionGroup.py
aviary/core/PreMissionGroup.py
aviary/core/__init__.py
aviary/docs/__init__.py
aviary/docs/_config.yml
aviary/docs/_toc.yml
aviary/docs/aviary.svg
aviary/docs/build_book.sh
aviary/docs/build_source_docs.py
aviary/docs/intro.md
aviary/docs/developer_guide/codebase_overview.ipynb
aviary/docs/developer_guide/coding_standards.ipynb
aviary/docs/developer_guide/contributing_guidelines.md
aviary/docs/developer_guide/debugging_env_from_github.md
aviary/docs/developer_guide/doctape.ipynb
aviary/docs/developer_guide/doctape_examples.ipynb
aviary/docs/developer_guide/how_to_contribute_docs.md
aviary/docs/developer_guide/unit_tests.md
aviary/docs/examples/OAS_subsystem.ipynb
aviary/docs/examples/additional_flight_phases.ipynb
aviary/docs/examples/coupled_aircraft_mission_optimization.ipynb
aviary/docs/examples/intro.ipynb
aviary/docs/examples/level_2_detailed_takeoff_and_landing.ipynb
aviary/docs/examples/modified_aircraft.csv
aviary/docs/examples/more_advanced_example.ipynb
aviary/docs/examples/multi_mission.ipynb
aviary/docs/examples/off_design_example.ipynb
aviary/docs/examples/reserve_missions.ipynb
aviary/docs/examples/simple_mission_example.ipynb
aviary/docs/examples/images/OAS_xdsm.PNG
aviary/docs/getting_started/expected_user_knowledge.md
aviary/docs/getting_started/input_csv_phase_info.ipynb
aviary/docs/getting_started/installation.md
aviary/docs/getting_started/now_what.md
aviary/docs/getting_started/onboarding.md
aviary/docs/getting_started/onboarding_ext_subsystem.ipynb
aviary/docs/getting_started/onboarding_level1.ipynb
aviary/docs/getting_started/onboarding_level2.ipynb
aviary/docs/getting_started/onboarding_level3.ipynb
aviary/docs/getting_started/tools_that_aviary_uses.md
aviary/docs/getting_started/what_aviary_does.md
aviary/docs/getting_started/images/N2_phases.PNG
aviary/docs/getting_started/images/N2_phases_links.PNG
aviary-0.9.10.dist-info/METADATA
aviary-0.9.10.dist-info/WHEEL
aviary-0.9.10.dist-info/entry_points.txt
aviary-0.9.10.dist-info/licenses/LICENSE
aviary-0.9.10.dist-info/RECORD
