Metadata-Version: 2.4
Name: aviary
Version: 0.9.10
License-Expression: Apache-2.0
License-File: LICENSE
Requires-Dist: dymos>=1.8.1
Requires-Dist: hvplot
Requires-Dist: importlib-resources
Requires-Dist: matplotlib
Requires-Dist: numpy<2
Requires-Dist: openmdao>=3.36.0
Requires-Dist: pandas
Requires-Dist: panel>=1.0.0
Requires-Dist: parameterized
Requires-Dist: simupy
Provides-Extra: all
Requires-Dist: ambiance; extra == 'all'
Requires-Dist: itables; extra == 'all'
Requires-Dist: myst-nb; extra == 'all'
Requires-Dist: openaerostruct; extra == 'all'
Requires-Dist: pre-commit; extra == 'all'
Requires-Dist: sphinx-book-theme==1.1.0; extra == 'all'
Requires-Dist: testflo; extra == 'all'
Provides-Extra: examples
Requires-Dist: ambiance; extra == 'examples'
Requires-Dist: itables; extra == 'examples'
Requires-Dist: openaerostruct; extra == 'examples'
Provides-Extra: test
Requires-Dist: myst-nb; extra == 'test'
Requires-Dist: pre-commit; extra == 'test'
Requires-Dist: sphinx-book-theme==1.1.0; extra == 'test'
Requires-Dist: testflo; extra == 'test'
